{
  "name": "Employee",
  "base": "PersistedModel",
  "idInjection": true,
  "options": {
    "validateUpsert": true
  },
  "properties": {
    "Name": {
      "type": "string",
      "required": true
    },
    "DOB": {
      "type": "date",
      "required": true
    },
    "ID": {
      "type": "string",
      "required": true
    },
    "Salary": {
      "type": "number"
    },
    "ReferralCode": {
      "type": "string"
    }
  },
  "validations": [],
  "relations": {},
  "acls": [],
  "methods": {}
}
